catalyst/__init__.py
catalyst/_configuration.py
catalyst/_revision.py
catalyst/_version.py
catalyst/compiled_functions.py
catalyst/compiler.py
catalyst/jax_primitives.py
catalyst/jax_primitives_utils.py
catalyst/jax_tracer.py
catalyst/jit.py
catalyst/pipelines.py
catalyst/qfunc.py
catalyst/api_extensions/__init__.py
catalyst/api_extensions/callbacks.py
catalyst/api_extensions/control_flow.py
catalyst/api_extensions/differentiation.py
catalyst/api_extensions/error_mitigation.py
catalyst/api_extensions/function_maps.py
catalyst/api_extensions/quantum_operators.py
catalyst/autograph/__init__.py
catalyst/autograph/ag_primitives.py
catalyst/autograph/operator_update.py
catalyst/autograph/transformer.py
catalyst/debug/__init__.py
catalyst/debug/assertion.py
catalyst/debug/callback.py
catalyst/debug/compiler_functions.py
catalyst/debug/instruments.py
catalyst/debug/printing.py
catalyst/device/__init__.py
catalyst/device/decomposition.py
catalyst/device/op_support.py
catalyst/device/qjit_device.py
catalyst/device/verification.py
catalyst/from_plxpr/__init__.py
catalyst/from_plxpr/control_flow.py
catalyst/from_plxpr/decompose.py
catalyst/from_plxpr/from_plxpr.py
catalyst/from_plxpr/qfunc_interpreter.py
catalyst/from_plxpr/qubit_handler.py
catalyst/ftqc/__init__.py
catalyst/ftqc/pipelines.py
catalyst/include/Gradient/IR/GradientDialect.h
catalyst/include/Gradient/IR/GradientInterfaces.h
catalyst/include/Gradient/IR/GradientInterfaces.h.inc
catalyst/include/Gradient/IR/GradientOps.h
catalyst/include/Gradient/IR/GradientOps.h.inc
catalyst/include/Gradient/IR/GradientOpsDialect.h.inc
catalyst/include/Gradient/IR/GradientOpsTypes.h.inc
catalyst/include/Gradient/Transforms/BufferizableOpInterfaceImpl.h
catalyst/include/Gradient/Transforms/EnzymeConstants.h
catalyst/include/Gradient/Transforms/Passes.h
catalyst/include/Gradient/Transforms/Passes.h.inc
catalyst/include/Gradient/Transforms/Patterns.h
pennylane_catalyst-0.14.0.dist-info/METADATA
pennylane_catalyst-0.14.0.dist-info/WHEEL
pennylane_catalyst-0.14.0.dist-info/entry_points.txt
pennylane_catalyst-0.14.0.dist-info/top_level.txt
pennylane_catalyst-0.14.0.dist-info/RECORD
pennylane_catalyst-0.14.0.dist-info/licenses/LICENSE
