Metadata-Version: 2.4
Name: pennylane_catalyst
Version: 0.14.0
Summary: A JIT compiler for hybrid quantum programs in PennyLane
Home-page: https://github.com/PennyLaneAI/catalyst
Maintainer: Xanadu Inc.
Maintainer-email: software@xanadu.ai
License: Apache License 2.0
Classifier: Environment :: Console
Classifier: Natural Language :: English
Classifier: Intended Audience :: Science/Research
Classifier: Development Status :: 3 - Alpha
Classifier: Operating System :: POSIX
Classifier: Operating System :: POSIX :: Linux
Classifier: Programming Language :: Python :: 3
Classifier: Programming Language :: Python :: 3.11
Classifier: Programming Language :: Python :: 3.12
Classifier: Programming Language :: Python :: 3.13
Classifier: Programming Language :: Python :: 3.14
Classifier: Programming Language :: Python :: 3 :: Only
Requires-Python: >=3.11
License-File: LICENSE
Requires-Dist: pennylane>=0.44.0
Requires-Dist: pennylane-lightning>=0.44.0
Requires-Dist: jax==0.7.1
Requires-Dist: jaxlib==0.7.1
Requires-Dist: numpy!=2.0.0
Requires-Dist: scipy-openblas32>=0.3.26
Requires-Dist: diastatic-malt>=2.15.2
Requires-Dist: xdsl==0.55.4
Requires-Dist: xdsl-jax==0.1.1
Dynamic: classifier
Dynamic: description
Dynamic: description-content-type
Dynamic: home-page
Dynamic: license
Dynamic: license-file
Dynamic: maintainer
Dynamic: maintainer-email
Dynamic: requires-dist
Dynamic: requires-python
Dynamic: summary
